lvmscraper/__init__.py
lvmscraper/__main__.py
lvmscraper/actor/__init__.py
lvmscraper/actor/actor.py
lvmscraper/actor/commands/__init__.py
lvmscraper/actor/commands/data.py
lvmscraper/actor/exceptions.py
lvmscraper/datastore.py
lvmscraper/etc/scraper.yml
lvmscraper/etc/scraper_key2fits.yml
lvmscraper/etc/scraper_sys2fits.yml
lvmscraper/etc/scraper_webserver.yml
lvmscraper/scraper.py
lvmscraper/webserver.py
sdss_lvmscraper-0.0.4.dist-info/entry_points.txt
sdss_lvmscraper-0.0.4.dist-info/LICENSE.md
sdss_lvmscraper-0.0.4.dist-info/WHEEL
sdss_lvmscraper-0.0.4.dist-info/METADATA
sdss_lvmscraper-0.0.4.dist-info/RECORD
