Metadata-Version: 2.1
Name: sdss-lvmscraper
Version: 0.0.4
Summary: LVM Instrument data scraper
Home-page: https://github.com/sdss/lvmscraper
License: BSD-3-Clause
Keywords: astronomy,software
Author: Florian Briegel
Author-email: briegel@mpia.de
Requires-Python: >=3.8,<4
Classifier: Intended Audience :: Science/Research
Classifier: License :: OSI Approved :: BSD License
Classifier: Natural Language :: English
Classifier: Operating System :: OS Independent
Classifier: Programming Language :: Python :: 3
Classifier: Programming Language :: Python :: 3.10
Classifier: Programming Language :: Python :: 3.8
Classifier: Programming Language :: Python :: 3.9
Classifier: Topic :: Documentation :: Sphinx
Classifier: Topic :: Software Development :: Libraries :: Python Modules
Requires-Dist: CherryPy (>=18.6.1)
Requires-Dist: pandas (>=1.4.0)
Requires-Dist: sdss-cluplus (>=0.0.18)
Project-URL: Documentation, https://sdss-lvmscraper.readthedocs.org
Project-URL: Repository, https://github.com/sdss/lvmscraper
